setup.py
fixtureload/__init__.py
fixtureload.egg-info/PKG-INFO
fixtureload.egg-info/SOURCES.txt
fixtureload.egg-info/dependency_links.txt
fixtureload.egg-info/not-zip-safe
fixtureload.egg-info/top_level.txt