Metadata-Version: 1.0
Name: fixtureload
Version: 0.2
Summary: Simple fixture loader
Home-page: https://github.com/ozanturksever/fixtureload
Author: Ozan Turksever
Author-email: ozan.turksever@gmail.com
License: MIT
Platform: UNKNOWN
